pygeodyntools-1.1.5.dist-info/licenses/LICENSE.txt
pygeotools/__init__.py
pygeotools/pygeotools.py
pygeotools/data/observatories_list.csv
pygeodyntools-1.1.5.dist-info/METADATA
pygeodyntools-1.1.5.dist-info/WHEEL
pygeodyntools-1.1.5.dist-info/top_level.txt
pygeodyntools-1.1.5.dist-info/RECORD
