Metadata-Version: 2.4
Name: pygeodyntools
Version: 1.1.5
Summary: pygeotools is a library allowing to load, manipulate and visualise geomagnetic models stemming from assimilation tools.
Author-email: Romain Claveau <romain.claveau@univ-grenoble-alpes.fr>, Nicolas Gillet <nicolas.gillet@univ-grenoble-alpes.fr>
Maintainer-email: Romain Claveau <romain.claveau@univ-grenoble-alpes.fr>
License:                     GNU GENERAL PUBLIC LICENSE
Project-URL: Homepage, https://gricad-gitlab.univ-grenoble-alpes.fr/claveaur/pygeotools
Project-URL: Issues, https://gricad-gitlab.univ-grenoble-alpes.fr/claveaur/pygeotools/-/issues
Keywords: geomagnetism,geomagnetic models,core flow reanalysis
Requires-Python: >=3.10
License-File: LICENSE.txt
Requires-Dist: cartopy
Requires-Dist: cdflib
Requires-Dist: cmocean
Requires-Dist: h5py
Requires-Dist: matplotlib
Requires-Dist: numpy>=1.10
Requires-Dist: scipy>=0.17
Dynamic: license-file
